{"LemonCake":{"name":"LemonCake","key":"fc883237-88f5-45e5-9e54-8c5378e50bdf","category":"product-reviews","date":"2021-03-07","title":"Lemon Cake","tags":"lemon, cake, flower"},"OldSchoolLemons":{"name":"OldSchoolLemons","key":"73488694-18a6-478a-88b2-cac49c7b9c2e","category":"product-reviews","date":"2021-03-01","title":"Old School Lemons","tags":"old, school, lemon, flower"},"StrawberryCake":{"name":"StrawberryCake","key":"382c6575-5f9c-4604-a070-3f3e10387027","category":"product-reviews","date":"2021-03-10","title":"Strawberry Cake","tags":"strawberry, cake, flower"},"White99":{"name":"White99","key":"35483bac-99d7-43cf-a8ab-b7efa86ef5e5","category":"product-reviews","date":"2021-03-07","title":"White 99%","tags":"flower"}}