[
  {
      "imageMD5": "",
      "taxSettings": [],
      "openPO": [],
      "salesTax": true,
      "skuNumber": "",
      "merchantId": 26013,
      "price": 217.18,
      "supplier": null,
      "variant": false,
      "id": 47071928,
      "barcode": "",
      "aliasName": "",
      "item": "",
      "modifierOptions": [],
      "markup": 0,
      "vaiantName": "",
      "displayChannelSettings": [
          {
              "channel": "REGISTER",
              "status": "ENABLED"
          },
          {
              "channel": "KIOSK",
              "status": "ENABLED"
          },
          {
              "channel": "ONLINE",
              "status": "ENABLED"
          }
      ],
      "tags": [],
      "categoryType": "Bundles",
      "bundles": [],
      "name": "620 Bundle",
      "needsLowInventoryAlert": false,
      "variantName": "",
      "partNo": "",
      "supplierId": 0,
      "color": "Blue",
      "discountSettings": [],
      "description": "Vaporizer, Grinder, Mini-Canlock, Large canlock ",
      "displayStatus": 0,
      "positionNumber": 16,
      "inventory": 0,
      "storeQty": 1,
      "createdOn": "06/03/2021 13:04:51",
      "modifiedOn": "06/03/2021 13:04:51",
      "productVariants": [],
      "productType": "REGULAR",
      "modiferAssociations": [],
      "cost": 0,
      "quantity": 1,
      "taxPercentage": 0,
      "dineOut": false,
      "merchantIdentification": 0,
      "altertThreshold": 0,
      "baseProductId": 0,
      "onlineStoreDisplayStatus": 0,
      "isVariable": 0,
      "optionIds": "",
      "categoryId": 1036898,
      "reorderQty": 0
  },
  {
      "imageMD5": "",
      "taxSettings": [],
      "openPO": [],
      "salesTax": true,
      "skuNumber": "",
      "merchantId": 26013,
      "price": 265.44,
      "supplier": null,
      "variant": false,
      "id": 47071960,
      "barcode": "",
      "aliasName": "",
      "item": "",
      "modifierOptions": [],
      "markup": 0,
      "vaiantName": "",
      "displayChannelSettings": [
          {
              "channel": "REGISTER",
              "status": "ENABLED"
          },
          {
              "channel": "KIOSK",
              "status": "ENABLED"
          },
          {
              "channel": "ONLINE",
              "status": "ENABLED"
          }
      ],
      "tags": [],
      "categoryType": "Bundles",
      "bundles": [],
      "name": "722 Bundle",
      "needsLowInventoryAlert": false,
      "variantName": "",
      "partNo": "",
      "supplierId": 0,
      "color": "Blue",
      "discountSettings": [],
      "description": "Vaporizer, Grinder, Mini-Canlock Jar, Regular Canlock Jar",
      "displayStatus": 0,
      "positionNumber": 17,
      "inventory": 0,
      "storeQty": 1,
      "createdOn": "06/03/2021 13:06:18",
      "modifiedOn": "06/03/2021 13:06:29",
      "productVariants": [],
      "productType": "REGULAR",
      "modiferAssociations": [],
      "cost": 0,
      "quantity": 1,
      "taxPercentage": 0,
      "dineOut": false,
      "merchantIdentification": 0,
      "altertThreshold": 0,
      "baseProductId": 0,
      "onlineStoreDisplayStatus": 0,
      "isVariable": 0,
      "optionIds": "",
      "categoryId": 1036898,
      "reorderQty": 0
  },
  {
      "imageMD5": "117ba4d35b8d670ea16f6843f078c376",
      "taxSettings": [],
      "openPO": [],
      "salesTax": true,
      "skuNumber": "",
      "merchantId": 26013,
      "price": 50,
      "supplier": null,
      "variant": false,
      "id": 43178704,
      "barcode": "",
      "aliasName": "O",
      "item": "",
      "modifierOptions": [],
      "markup": 0,
      "vaiantName": "",
      "displayChannelSettings": [
          {
              "channel": "REGISTER",
              "status": "ENABLED"
          },
          {
              "channel": "KIOSK",
              "status": "ENABLED"
          },
          {
              "channel": "ONLINE",
              "status": "ENABLED"
          }
      ],
      "tags": [],
      "categoryType": "Bundles",
      "bundles": [],
      "name": "Canlock Bundle",
      "needsLowInventoryAlert": false,
      "variantName": "",
      "partNo": "",
      "supplierId": 0,
      "color": "Blue",
      "discountSettings": [],
      "description": "",
      "displayStatus": 0,
      "positionNumber": 15,
      "inventory": 0,
      "storeQty": 1,
      "createdOn": "10/13/2020 08:16:40",
      "modifiedOn": "12/22/2020 09:47:02",
      "productVariants": [],
      "productType": "REGULAR",
      "modiferAssociations": [],
      "cost": 25,
      "quantity": 1,
      "taxPercentage": 0,
      "dineOut": false,
      "merchantIdentification": 0,
      "altertThreshold": 0,
      "baseProductId": 0,
      "onlineStoreDisplayStatus": 0,
      "isVariable": 0,
      "optionIds": "",
      "categoryId": 1036898,
      "reorderQty": 0
  },
  {
      "imageMD5": "a51fd1ae9fde1090e75aa60cd331877e",
      "taxSettings": [],
      "openPO": [],
      "salesTax": true,
      "skuNumber": "",
      "merchantId": 26013,
      "price": 100,
      "supplier": null,
      "variant": false,
      "id": 42994536,
      "barcode": "",
      "aliasName": "",
      "item": "",
      "modifierOptions": [],
      "markup": 0,
      "vaiantName": "",
      "displayChannelSettings": [
          {
              "channel": "REGISTER",
              "status": "ENABLED"
          },
          {
              "channel": "KIOSK",
              "status": "ENABLED"
          },
          {
              "channel": "ONLINE",
              "status": "ENABLED"
          }
      ],
      "tags": [],
      "categoryType": "Bundles",
      "bundles": [],
      "name": "Rest & Relax BUNDLE",
      "needsLowInventoryAlert": false,
      "variantName": "",
      "partNo": "",
      "supplierId": 0,
      "color": "Blue",
      "discountSettings": [],
      "description": "Rest & Relax 25mg caps",
      "displayStatus": 0,
      "positionNumber": 3.875,
      "inventory": 0,
      "storeQty": 1,
      "createdOn": "09/29/2020 10:56:10",
      "modifiedOn": "10/06/2020 17:48:56",
      "productVariants": [],
      "productType": "REGULAR",
      "modiferAssociations": [],
      "cost": 70,
      "quantity": 1,
      "taxPercentage": 0,
      "dineOut": false,
      "merchantIdentification": 0,
      "altertThreshold": 0,
      "baseProductId": 0,
      "onlineStoreDisplayStatus": 0,
      "isVariable": 0,
      "optionIds": "",
      "categoryId": 1036898,
      "reorderQty": 0
  }
]